poos/__init__.py
poos/api/__init__.py
poos/api/tencent/__init__.py
poos/api/tencent/cos.py
poos/core/TencentCos.py
poos/core/__init__.py
poos/lib/__init__.py
poos/lib/get_toml.py
tests/__init__.py
tests/test_tools.py
poos-0.0.2.dist-info/LICENSE
poos-0.0.2.dist-info/METADATA
poos-0.0.2.dist-info/WHEEL
poos-0.0.2.dist-info/top_level.txt
poos-0.0.2.dist-info/RECORD
