Metadata-Version: 2.1
Name: poos
Version: 0.0.2
Summary: pip install poos
Home-page: http://python-office.com/
Author: CoderWanFeng
Author-email: 1957875073@qq.com
License: MIT
Project-URL: Bug Tracker, https://github.com/CoderWanFeng/poos/issues
Project-URL: Documentation, https://github.com/CoderWanFeng/poos/blob/master/README.md
Project-URL: Source Code, https://github.com/CoderWanFeng/poos
Platform: any
Requires-Python: >=3.7
License-File: LICENSE
Requires-Dist: cos-python-sdk-v5
Requires-Dist: toml
